[
  {
    "german": "eine Tüte",
    "english": "a bag (of)",
    "part of speech": "noun",
    "plural and inflected": "Tüten",
    "level": "Quantities_and_measures"
  },
  {
    "german": "eine Tafel",
    "english": "a bar (of)",
    "part of speech": "noun",
    "plural and inflected": "Tafeln",
    "level": "Quantities_and_measures"
  },
  {
    "german": "eine Flasche",
    "english": "a bottle (of)",
    "part of speech": "noun",
    "plural and inflected": "Flaschen",
    "level": "Quantities_and_measures"
  },
  {
    "german": "ein Dutzend",
    "english": "a dozen",
    "part of speech": "noun",
    "plural and inflected": "Dutzende",
    "level": "Quantities_and_measures"
  },
  {
    "german": "ein Glas",
    "english": "a glass (of)",
    "part of speech": "noun",
    "plural and inflected": "Gläser",
    "level": "Quantities_and_measures"
  },
  {
    "german": "ein bisschen",
    "english": "a little (of), a bit (of)",
    "part of speech": "adverb, preposition",
    "plural and inflected": "",
    "level": "Quantities_and_measures"
  },
  {
    "german": "eine Packung",
    "english": "a packet (of)",
    "part of speech": "noun",
    "plural and inflected": "Packungen",
    "level": "Quantities_and_measures"
  },
  {
    "german": "ein Stück",
    "english": "a piece (of)",
    "part of speech": "noun",
    "plural and inflected": "Stücke",
    "level": "Quantities_and_measures"
  },
  {
    "german": "eine Scheibe",
    "english": "a slice (of)",
    "part of speech": "noun",
    "plural and inflected": "Scheiben",
    "level": "Quantities_and_measures"
  },
  {
    "german": "ein Drittel",
    "english": "a third (of)",
    "part of speech": "noun",
    "plural and inflected": "Drittel",
    "level": "Quantities_and_measures"
  },
  {
    "german": "eine Dose",
    "english": "a tin (of)",
    "part of speech": "noun",
    "plural and inflected": "Dosen",
    "level": "Quantities_and_measures"
  },
  {
    "german": "eine Schachtel",
    "english": "a (cardboard) box (of)",
    "part of speech": "noun",
    "plural and inflected": "Schachteln",
    "level": "Quantities_and_measures"
  },
  {
    "german": "eine Kiste",
    "english": "a (wooden) box (of)",
    "part of speech": "noun",
    "plural and inflected": "Kisten",
    "level": "Quantities_and_measures"
  },
  {
    "german": "genug",
    "english": "enough",
    "part of speech": "adverb",
    "plural and inflected": "",
    "level": "Quantities_and_measures"
  },
  {
    "german": "viel",
    "english": "many, lots",
    "part of speech": "adverb",
    "plural and inflected": "",
    "level": "Quantities_and_measures"
  },
  {
    "german": "mehrere",
    "english": "several",
    "part of speech": "adverb",
    "plural and inflected": "",
    "level": "Quantities_and_measures"
  }
]