[
  {
    "term": "Factor Markets",
    "meaning": "The buying and selling of land, labour and capital."
  },
  {
    "term": "Product Markets",
    "meaning": "A market in which products are bought and sold and prices are determined by the interaction of demand and supply."
  },
  {
    "term": "Primary sector",
    "meaning": "Industries involved in extracting raw materials (agriculture, fishing, forestry, mining)."
  },
  {
    "term": "Secondary Sector",
    "meaning": "Manufacturing or construction industries. Ones that make things (factories, carpenters, bakers, builders)."
  },
  {
    "term": "Tertiary Sector",
    "meaning": "Industries that provide a service (banking, solicitors, teachers, police forces, doctors)."
  },
  {
    "term": "Division of Labour",
    "meaning": "The allocation of workers to specific tasks in the production line."
  },
  {
    "term": "Exchange",
    "meaning": "Where buyers and sellers come together in a market place to negotiate prices."
  },
  {
    "term": "Job Rotation",
    "meaning": "Where employee move between departments"
  },
  {
    "term": "Specialisation",
    "meaning": "Where a country, business or worker focuses on the production of a limited range of products or services in order to gain greater efficiency; with the aim of increasing productivity & lowering costs."
  }
]
