[
  {
    "german": "schlecht",
    "english": "bad",
    "part of speech": "adjective",
    "plural and inflected": "",
    "level": "Weather"
  },
  {
    "german": "heiter",
    "english": "bright",
    "part of speech": "adjective",
    "plural and inflected": "",
    "level": "Weather"
  },
  {
    "german": "das Klima",
    "english": "climate",
    "part of speech": "noun",
    "plural and inflected": "",
    "level": "Weather"
  },
  {
    "german": "die Wolke",
    "english": "cloud",
    "part of speech": "noun",
    "plural and inflected": "die Wolken",
    "level": "Weather"
  },
  {
    "german": "wolkig",
    "english": "cloudy (1/2 of sky covered)",
    "part of speech": "adjective",
    "plural and inflected": "",
    "level": "Weather"
  },
  {
    "german": "bewölkt",
    "english": "cloudy (5/8 of sky covered)",
    "part of speech": "adjective",
    "plural and inflected": "",
    "level": "Weather"
  },
  {
    "german": "kalt",
    "english": "cold",
    "part of speech": "adjective",
    "plural and inflected": "",
    "level": "Weather"
  },
  {
    "german": "der Grad",
    "english": "degree (temperature)",
    "part of speech": "noun",
    "plural and inflected": "die Grade",
    "level": "Weather"
  },
  {
    "german": "trocken",
    "english": "dry",
    "part of speech": "adjective",
    "plural and inflected": "",
    "level": "Weather"
  },
  {
    "german": "der Nebel",
    "english": "fog",
    "part of speech": "noun",
    "plural and inflected": "die Nebel",
    "level": "Weather"
  },
  {
    "german": "neblig",
    "english": "foggy",
    "part of speech": "adjective",
    "plural and inflected": "",
    "level": "Weather"
  },
  {
    "german": "die Hitze",
    "english": "heat",
    "part of speech": "noun",
    "plural and inflected": "",
    "level": "Weather"
  },
  {
    "german": "die Höchsttemperatur",
    "english": "highest temperature",
    "part of speech": "noun",
    "plural and inflected": "die Höchsttemperaturen",
    "level": "Weather"
  },
  {
    "german": "heiß",
    "english": "hot",
    "part of speech": "adjective",
    "plural and inflected": "",
    "level": "Weather"
  },
  {
    "german": "im Osten",
    "english": "in the east",
    "part of speech": "expression",
    "plural and inflected": "",
    "level": "Weather"
  },
  {
    "german": "im Norden",
    "english": "in the north",
    "part of speech": "expression",
    "plural and inflected": "",
    "level": "Weather"
  },
  {
    "german": "im Süden",
    "english": "in the south",
    "part of speech": "expression",
    "plural and inflected": "",
    "level": "Weather"
  },
  {
    "german": "im Westen",
    "english": "in the west",
    "part of speech": "expression",
    "plural and inflected": "",
    "level": "Weather"
  },
  {
    "german": "es friert",
    "english": "it is freezing",
    "part of speech": "expression",
    "plural and inflected": "",
    "level": "Weather"
  },
  {
    "german": "es blitzt",
    "english": "there is lightning (lit: it is flashing)",
    "part of speech": "expression",
    "plural and inflected": "",
    "level": "Weather"
  },
  {
    "german": "es regnet",
    "english": "it is raining",
    "part of speech": "expression",
    "plural and inflected": "",
    "level": "Weather"
  },
  {
    "german": "es schneit",
    "english": "it is snowing",
    "part of speech": "expression",
    "plural and inflected": "",
    "level": "Weather"
  },
  {
    "german": "es donnert",
    "english": "it is thundering",
    "part of speech": "expression",
    "plural and inflected": "",
    "level": "Weather"
  },
  {
    "german": "die Tiefsttemperatur",
    "english": "lowest temperature",
    "part of speech": "noun",
    "plural and inflected": "die Tiefsttemperaturen",
    "level": "Weather"
  },
  {
    "german": "bedeckt",
    "english": "overcast",
    "part of speech": "adjective",
    "plural and inflected": "",
    "level": "Weather"
  },
  {
    "german": "der Regen",
    "english": "rain",
    "part of speech": "noun",
    "plural and inflected": "die Regen",
    "level": "Weather"
  },
  {
    "german": "regnerisch",
    "english": "rainy",
    "part of speech": "adjective",
    "plural and inflected": "",
    "level": "Weather"
  },
  {
    "german": "die Jahreszeit",
    "english": "season",
    "part of speech": "noun",
    "plural and inflected": "die Jahreszeiten",
    "level": "Weather"
  },
  {
    "german": "der Himmel",
    "english": "sky",
    "part of speech": "noun",
    "plural and inflected": "die Himmel",
    "level": "Weather"
  },
  {
    "german": "der Schnee",
    "english": "snow",
    "part of speech": "noun",
    "plural and inflected": "",
    "level": "Weather"
  },
  {
    "german": "der Sturm",
    "english": "storm",
    "part of speech": "noun",
    "plural and inflected": "die Stürme",
    "level": "Weather"
  },
  {
    "german": "die Sonne",
    "english": "sun",
    "part of speech": "noun",
    "plural and inflected": "die Sonnen",
    "level": "Weather"
  },
  {
    "german": "sonnig",
    "english": "sunny",
    "part of speech": "adjective, adverb",
    "plural and inflected": "",
    "level": "Weather"
  },
  {
    "german": "die Sonne scheint",
    "english": "the sun is shining",
    "part of speech": "expression",
    "plural and inflected": "",
    "level": "Weather"
  },
  {
    "german": "das Gewitter",
    "english": "thunderstorm",
    "part of speech": "noun",
    "plural and inflected": "die Gewitter",
    "level": "Weather"
  },
  {
    "german": "wechseln",
    "english": "to change",
    "part of speech": "verb",
    "plural and inflected": "wechselte; hat gewechselt",
    "level": "Weather"
  },
  {
    "german": "frieren",
    "english": "to freeze",
    "part of speech": "verb",
    "plural and inflected": "fror; hat gefroren",
    "level": "Weather"
  },
  {
    "german": "regnen",
    "english": "to rain",
    "part of speech": "verb",
    "plural and inflected": "regnete; hat geregnet",
    "level": "Weather"
  },
  {
    "german": "scheinen",
    "english": "to seem, shine",
    "part of speech": "verb",
    "plural and inflected": "schien; hat geschienen",
    "level": "Weather"
  },
  {
    "german": "schneien",
    "english": "to snow",
    "part of speech": "verb",
    "plural and inflected": "schneite; hat geschneit",
    "level": "Weather"
  },
  {
    "german": "das Wetter",
    "english": "weather",
    "part of speech": "noun",
    "plural and inflected": "die Wetter",
    "level": "Weather"
  },
  {
    "german": "der Wetterbericht",
    "english": "weather report",
    "part of speech": "noun",
    "plural and inflected": "die Wetterberichte",
    "level": "Weather"
  },
  {
    "german": "der Wind",
    "english": "wind",
    "part of speech": "noun",
    "plural and inflected": "die Winde",
    "level": "Weather"
  },
  {
    "german": "windig",
    "english": "windy",
    "part of speech": "adjective",
    "plural and inflected": "",
    "level": "Weather"
  },
  {
    "german": "die Durchschnittstemperatur",
    "english": "average temperature",
    "part of speech": "noun",
    "plural and inflected": "die Durchschnittstemperaturen",
    "level": "Weather"
  },
  {
    "german": "die Aufheiterung",
    "english": "bright spell",
    "part of speech": "noun",
    "plural and inflected": "die Aufheiterungen",
    "level": "Weather"
  },
  {
    "german": "wechselhaft",
    "english": "changeable",
    "part of speech": "adjective",
    "plural and inflected": "",
    "level": "Weather"
  },
  {
    "german": "der Hagel",
    "english": "hail",
    "part of speech": "noun",
    "plural and inflected": "",
    "level": "Weather"
  },
  {
    "german": "niedrig",
    "english": "low",
    "part of speech": "adjective",
    "plural and inflected": "",
    "level": "Weather"
  },
  {
    "german": "der Niederschlag",
    "english": "rainfall",
    "part of speech": "noun",
    "plural and inflected": "die Niederschläge",
    "level": "Weather"
  },
  {
    "german": "der Schauer",
    "english": "shower",
    "part of speech": "noun",
    "plural and inflected": "die Schauer",
    "level": "Weather"
  },
  {
    "german": "stürmisch",
    "english": "stormy",
    "part of speech": "adjective",
    "plural and inflected": "",
    "level": "Weather"
  },
  {
    "german": "aufklären",
    "english": "to brighten up",
    "part of speech": "verb",
    "plural and inflected": "klärte auf; hat aufgeklärt",
    "level": "Weather"
  },
  {
    "german": "hageln",
    "english": "to hail",
    "part of speech": "verb",
    "plural and inflected": "hagelte; hat gehagelt",
    "level": "Weather"
  },
  {
    "german": "die Wettervorhersage",
    "english": "weather forecast",
    "part of speech": "noun",
    "plural and inflected": "die Wettervorhersagen",
    "level": "Weather"
  }
]